{
  "link": {
    "osx/zshrc_osx":    "~/.zshrc_local",
    "osx/gitconfig":    "~/.gitconfig_local",
    "../mutt/setup-local.muttrc":   "~/.mutt_setup",
    "../mbsyncrc":      "~/.mbsyncrc",
    "../bin/battery-saver": "~/bin/battery-saver",
    "../bin/sync-gmail": "~/bin/sync-gmail",
    "osx/com.simpod.gmail.sync.plist": "~/Library/LaunchAgents/com.simpod.gmail.sync.plist"
  },

  "commands": [
    "#brew tap homebrew/bundle && brew bundle",
    "git config --global credential.helper osxkeychain"
  ]
}
